{
    "bridge": {
        "name": "Homebridge",
        "username": "CC:22:3D:E3:CE:30",
        "port": 51826,
        "pin": "031-45-154"
    },
    
    "description": "This is an example configuration file with one fake accessory and one fake platform. You can use this as a template for creating your own configuration file containing devices you actually own.",

    "accessories": [
        {
            "accessory": "Http-SecuritySystem",
            "name": "Alarm System",
            "key": "YOUR API KEY FROM ALARMDECODER GUI",
            "urls": {
                "stay": { "url": "http://YOURIP:YOURPORT/api/v1/alarmdecoder/send", "body": "11113" },
                "away": { "url": "http://YOURIP:YOURPORT/api/v1/alarmdecoder/send", "body": "11112" },
                "night": { "url": "http://YOURIP:YOURPORT/api/v1/alarmdecoder/send", "body": "111133" },
                "disarm": { "url": "http://YOURIP:YOURPORT/api/v1/alarmdecoder/send", "body": "11111" },
                "readCurrentState": { "url": "http://YOURIP:YOURPORT/api/v1/alarmdecoder", "body": "" },
                "readTargetState": { "url": "http://YOURIP:YOURPORT/api/v1/alarmdecoder", "body": "" }
            }
        }
    ]

}
